Workbook

Sheet Slope Summary
A1: Scale Curve Slope Estimates
A2: Fit: ln(cost per sub) = a + b*ln(subscribers). Each doubling of subscribers multiplies cost per sub by 2^b.
A4: Company / period | B4: Exponent b (SLOPE) | C4: R-squared | D4: Scale-curve ratio (2^b) | E4: Change in cost/sub per doubling | F4: Subscriber growth over period
A5: Verizon 2014-2025 (all years) | B5: =SLOPE(Verizon!H5:H16,Verizon!G5:G16) -> -0.76697244 | C5: =RSQ(Verizon!H5:H16,Verizon!G5:G16) -> 0.88930818 | D5: =2^B5 -> 0.58764939 | E5: =D5-1 -> -0.41235061 | F5: =Verizon!E16/Verizon!E5-1 -> 0.35859519
A6: Verizon 2014-2020 (before TracFone) | B6: =SLOPE(Verizon!H5:H11,Verizon!G5:G11) -> -0.77657065 | C6: =RSQ(Verizon!H5:H11,Verizon!G5:G11) -> 0.42107877 | D6: =2^B6 -> 0.58375275 | E6: =D6-1 -> -0.41624725 | F6: =Verizon!E11/Verizon!E5-1 -> 0.11829945
A7: Verizon 2021-2025 (after TracFone) | B7: =SLOPE(Verizon!H12:H16,Verizon!G12:G16) -> 0.2824135 | C7: =RSQ(Verizon!H12:H16,Verizon!G12:G16) -> 0.017150831 | D7: =2^B7 -> 1.2162278 | E7: =D7-1 -> 0.21622783 | F7: =Verizon!E16/Verizon!E12-1 -> 0.035211268
A8: T-Mobile 2014-2025 (all years) | B8: =SLOPE('T-Mobile'!H5:H16,'T-Mobile'!G5:G16) -> 0.16996923 | C8: =RSQ('T-Mobile'!H5:H16,'T-Mobile'!G5:G16) -> 0.1533538 | D8: =2^B8 -> 1.1250345 | E8: =D8-1 -> 0.12503449 | F8: ='T-Mobile'!E16/'T-Mobile'!E5-1 -> 1.5890909
A9: T-Mobile 2014-2019 (before Sprint) | B9: =SLOPE('T-Mobile'!H5:H10,'T-Mobile'!G5:G10) -> -0.19287004 | C9: =RSQ('T-Mobile'!H5:H10,'T-Mobile'!G5:G10) -> 0.59342837 | D9: =2^B9 -> 0.87486357 | E9: =D9-1 -> -0.12513643 | F9: ='T-Mobile'!E10/'T-Mobile'!E5-1 -> 0.56363636
A10: T-Mobile 2020-2025 (after Sprint) | B10: =SLOPE('T-Mobile'!H11:H16,'T-Mobile'!G11:G16) -> -0.95107052 | C10: =RSQ('T-Mobile'!H11:H16,'T-Mobile'!G11:G16) -> 0.70106973 | D10: =2^B10 -> 0.51724851 | E10: =D10-1 -> -0.48275149 | F10: ='T-Mobile'!E16/'T-Mobile'!E11-1 -> 0.39471107
A12: Latest-year cost per subscriber (2025)
A13: Verizon | B13: =Verizon!F16 -> 721.29932
A14: T-Mobile | B14: ='T-Mobile'!F16 -> 491.78371
A15: Lowest cost per sub | B15: =IF(B14<B13,"T-Mobile","Verizon") -> T-Mobile
A17: Definitions
A18: Total costs = total operating revenues - operating income = total operating expenses (cost of services, cost of equipment, SG&A, depreciation & amortization, impairments). Not just cost of services.
A19: Verizon costs are consolidated (include Fios/wireline, ~20% of revenue), because Verizon no longer reports a standalone wireless P&L after 2018. Subscribers = wireless retail connections (Consumer + Business).
A20: T-Mobile costs are consolidated; T-Mobile is almost entirely wireless. Subscribers = total postpaid + prepaid customers.
A21: A ratio below 100% means cost per subscriber falls as the company grows (e.g., 80% = costs fall 20% with each doubling). Above 100% = costs rise.

Sheet Verizon
A1: Verizon - Wireless Scale Curve Data
A2: Blue = input from filings. Black = formula. Yellow rows = subscriber count estimated (see note column).
A4: Year | B4: Total operating revenues ($M) | C4: Operating income ($M) | D4: Total costs ($M) = Revenue - Operating income | E4: Wireless retail connections (millions) | F4: Cost per subscriber ($ per year) | G4: LN(subscribers) | H4: LN(cost per sub) | I4: Note / source of subscriber figure
A5: 2014 | B5: 127079 | C5: 27144 | D5: =B5-C5 -> 99935 | E5: 108.2 | F5: =D5/E5 -> 923.61368 | G5: =LN(E5) -> 4.6839814 | H5: =LN(F5) -> 6.8282939 | I5: 10-K table: 108,211K retail connections
A6: 2015 | B6: 131620 | C6: 30615 | D6: =B6-C6 -> 101005 | E6: 112.1 | F6: =D6/E6 -> 901.02587 | G6: =LN(E6) -> 4.7193913 | H6: =LN(F6) -> 6.803534 | I6: 10-K table: 112,108K retail connections
A7: 2016 | B7: 125980 | C7: 29249 | D7: =B7-C7 -> 96731 | E7: 114.2 | F7: =D7/E7 -> 847.03152 | G7: =LN(E7) -> 4.7379513 | H7: =LN(F7) -> 6.7417379 | I7: 2016 Annual Report: 114,243K retail connections
A8: 2017 | B8: 126034 | C8: 27425 | D8: =B8-C8 -> 98609 | E8: 116.3 | F8: =D8/E8 -> 847.88478 | G8: =LN(E8) -> 4.7561731 | H8: =LN(F8) -> 6.7427448 | I8: 2017 10-K: 116,257K retail connections
A9: 2018 | B9: 130863 | C9: 22278 | D9: =B9-C9 -> 108585 | E9: 118 | F9: =D9/E9 -> 920.21186 | G9: =LN(E9) -> 4.7706846 | H9: =LN(F9) -> 6.8246039 | I9: 2018 10-K: 118.0M retail connections
A10: 2019 | B10: 131868 | C10: 30378 | D10: =B10-C10 -> 101490 | E10: 119.5 | F10: =D10/E10 -> 849.2887 | G10: =LN(E10) -> 4.7833164 | H10: =LN(F10) -> 6.7443992 | I10: ESTIMATE: 2019 10-K Consumer 94.5M + Business ~25M (segments reorganized in 2019)
A11: 2020 | B11: 128292 | C11: 28798 | D11: =B11-C11 -> 99494 | E11: 121 | F11: =D11/E11 -> 822.26446 | G11: =LN(E11) -> 4.7957905 | H11: =LN(F11) -> 6.7120621 | I11: ESTIMATE: 2020 10-K Consumer ~94M + Business ~27M
A12: 2021 | B12: 133613 | C12: 32448 | D12: =B12-C12 -> 101165 | E12: 142 | F12: =D12/E12 -> 712.42958 | G12: =LN(E12) -> 4.9558271 | H12: =LN(F12) -> 6.5686811 | I12: ESTIMATE: 2021 10-K Consumer ~115M (incl. TracFone, acquired 11/23/2021) + Business ~27M
A13: 2022 | B13: 136835 | C13: 30467 | D13: =B13-C13 -> 106368 | E13: 144 | F13: =D13/E13 -> 738.66667 | G13: =LN(E13) -> 4.9698133 | H13: =LN(F13) -> 6.6048468 | I13: ESTIMATE: 2022 10-K Consumer ~115M + Business ~29M
A14: 2023 | B14: 133974 | C14: 22877 | D14: =B14-C14 -> 111097 | E14: 144.8 | F14: =D14/E14 -> 767.24448 | G14: =LN(E14) -> 4.9753535 | H14: =LN(F14) -> 6.6428055 | I14: 2023: Consumer 114.97M + Business 29.78M
A15: 2024 | B15: 134788 | C15: 28686 | D15: =B15-C15 -> 106102 | E15: 146 | F15: =D15/E15 -> 726.72603 | G15: =LN(E15) -> 4.9836066 | H15: =LN(F15) -> 6.5885496 | I15: 2024 10-K: "over 146 million" wireless retail connections
A16: 2025 | B16: 138191 | C16: 32160 | D16: =B16-C16 -> 106031 | E16: 147 | F16: =D16/E16 -> 721.29932 | G16: =LN(E16) -> 4.9904326 | H16: =LN(F16) -> 6.5810542 | I16: 2025 10-K: ~147M wireless retail connections (Consumer ~116M + Business ~31M)

Sheet T-Mobile
A1: T-Mobile - Wireless Scale Curve Data
A2: Blue = input from filings. Black = formula. Yellow rows = subscriber count estimated (see note column).
A4: Year | B4: Total operating revenues ($M) | C4: Operating income ($M) | D4: Total costs ($M) = Revenue - Operating income | E4: Total customers (millions) | F4: Cost per subscriber ($ per year) | G4: LN(subscribers) | H4: LN(cost per sub) | I4: Note / source of subscriber figure
A5: 2014 | B5: 29564 | C5: 1416 | D5: =B5-C5 -> 28148 | E5: 55 | F5: =D5/E5 -> 511.78182 | G5: =LN(E5) -> 4.0073332 | H5: =LN(F5) -> 6.2378984 | I5: 2014 10-K: 55,018K total customers
A6: 2015 | B6: 32467 | C6: 2479 | D6: =B6-C6 -> 29988 | E6: 63.3 | F6: =D6/E6 -> 473.74408 | G6: =LN(E6) -> 4.1478853 | H6: =LN(F6) -> 6.1606673 | I6: 63.3M total customers (revenue/op. income as recast in 2017 10-K)
A7: 2016 | B7: 37490 | C7: 4050 | D7: =B7-C7 -> 33440 | E7: 71.5 | F7: =D7/E7 -> 467.69231 | G7: =LN(E7) -> 4.2696974 | H7: =LN(F7) -> 6.1478106 | I7: 71.5M total customers (recast in 2017 10-K)
A8: 2017 | B8: 40604 | C8: 4888 | D8: =B8-C8 -> 35716 | E8: 72.6 | F8: =D8/E8 -> 491.95592 | G8: =LN(E8) -> 4.2849649 | H8: =LN(F8) -> 6.1983891 | I8: 2017 10-K: 72.6M total customers
A9: 2018 | B9: 43310 | C9: 5309 | D9: =B9-C9 -> 38001 | E9: 79.7 | F9: =D9/E9 -> 476.8005 | G9: =LN(E9) -> 4.3782696 | H9: =LN(F9) -> 6.1670982 | I9: 79.7M total customers
A10: 2019 | B10: 44998 | C10: 5722 | D10: =B10-C10 -> 39276 | E10: 86 | F10: =D10/E10 -> 456.69767 | G10: =LN(E10) -> 4.4543473 | H10: =LN(F10) -> 6.1240216 | I10: 86.0M total customers
A11: 2020 | B11: 68397 | C11: 6636 | D11: =B11-C11 -> 61761 | E11: 102.1 | F11: =D11/E11 -> 604.90695 | G11: =LN(E11) -> 4.6259527 | H11: =LN(F11) -> 6.4050747 | I11: 102.1M total customers (Sprint merger closed 4/1/2020)
A12: 2021 | B12: 80118 | C12: 6892 | D12: =B12-C12 -> 73226 | E12: 108.7 | F12: =D12/E12 -> 673.65225 | G12: =LN(E12) -> 4.6885918 | H12: =LN(F12) -> 6.512714 | I12: 108.7M total customers
A13: 2022 | B13: 79571 | C13: 6543 | D13: =B13-C13 -> 73028 | E13: 113.6 | F13: =D13/E13 -> 642.85211 | G13: =LN(E13) -> 4.7326835 | H13: =LN(F13) -> 6.4659147 | I13: 113.6M total customers
A14: 2023 | B14: 78558 | C14: 14266 | D14: =B14-C14 -> 64292 | E14: 119.7 | F14: =D14/E14 -> 537.10944 | G14: =LN(E14) -> 4.7849886 | H14: =LN(F14) -> 6.2862019 | I14: 119.7M total customers
A15: 2024 | B15: 81400 | C15: 18010 | D15: =B15-C15 -> 63390 | E15: 129.5 | F15: =D15/E15 -> 489.49807 | G15: =LN(E15) -> 4.8636809 | H15: =LN(F15) -> 6.1933805 | I15: 129.5M total customers
A16: 2025 | B16: 88309 | C16: 18279 | D16: =B16-C16 -> 70030 | E16: 142.4 | F16: =D16/E16 -> 491.78371 | G16: =LN(E16) -> 4.95864 | H16: =LN(F16) -> 6.198039 | I16: 142.4M total customers (Q4 2025 earnings release)

Sheet Sources
A1: Data Sources
A3: Company | B3: Data item | C3: Document | D3: URL
A4: Verizon | B4: 2014-2018 revenues & operating income (recast five-year table) | C4: Verizon 2018 Annual Report, Selected Financial Data | D4: https://www.verizon.com/about/sites/default/files/2018-Verizon-Annual-Report-Financial-Section.pdf
A5: Verizon | B5: 2019-2021 revenues & operating income | C5: Verizon FY2021 Form 10-K; 4Q21 Financial & Operating Information | D5: https://www.sec.gov/Archives/edgar/data/732712/000073271222000008/vz-20211231.htm
A6: Verizon | B6: 2022-2024 revenues & operating income | C6: Verizon FY2024 Form 10-K (segment reconciliation) | D6: https://www.sec.gov/Archives/edgar/data/732712/000073271225000006/vz-20241231.htm
A7: Verizon | B7: 2025 revenues & operating income | C7: Verizon 4Q25 Financial & Operating Information; FY2025 10-K | D7: https://www.verizon.com/about/sites/default/files/2026-02/vz_4q25_foi_013026r.pdf
A8: Verizon | B8: 2014-2015 retail connections | C8: Verizon 2015 Annual Report | D8: https://www.verizon.com/about/sites/default/files/15_vz_ar.pdf
A9: Verizon | B9: 2016 retail connections | C9: Verizon 2016 Annual Report | D9: https://www.verizon.com/about/sites/default/files/Verizon-AnnualReport2016.pdf
A10: Verizon | B10: 2017 retail connections | C10: Verizon FY2017 Form 10-K | D10: https://www.sec.gov/Archives/edgar/data/732712/000073271218000009/a201710-k.htm
A11: Verizon | B11: 2018 retail connections | C11: Verizon FY2018 Form 10-K | D11: https://www.sec.gov/Archives/edgar/data/732712/000073271219000012/a2018q410-k.htm
A12: Verizon | B12: 2019-2020 connections (Consumer + Business) | C12: Verizon FY2020 Form 10-K, Item 1 | D12: https://www.verizon.com/about/sites/default/files/2020-Annual-Report-on-Form-10-K.PDF
A13: Verizon | B13: 2021 connections; TracFone close date | C13: Verizon FY2021 Form 10-K | D13: https://www.sec.gov/Archives/edgar/data/732712/000073271222000008/vz-20211231.htm
A14: Verizon | B14: 2022 connections | C14: Verizon FY2022 Form 10-K | D14: https://www.verizon.com/about/sites/default/files/2022-Annual-Report-on-Form-10K.pdf
... A24: Both | B24: Cross-check of yearly totals | C24: Macrotrends (TMUS revenue / operating income history) | D24: https://www.macrotrends.net/stocks/charts/TMUS/t-mobile-us/operating-income
A26: Verify each figure against the filing before submitting; some subscriber counts are rounded figures stated in 10-K text ("approximately X million").
